Nondimensionalization_UssopSniperKing/__init__.py
Nondimensionalization_UssopSniperKing/numbers.py
Nondimensionalization_UssopSniperKing-0.0.2.dist-info/LICENSE
Nondimensionalization_UssopSniperKing-0.0.2.dist-info/METADATA
Nondimensionalization_UssopSniperKing-0.0.2.dist-info/WHEEL
Nondimensionalization_UssopSniperKing-0.0.2.dist-info/top_level.txt
Nondimensionalization_UssopSniperKing-0.0.2.dist-info/RECORD
