Metadata-Version: 2.1
Name: Nondimensionalization-UssopSniperKing
Version: 0.0.2
Summary: A small package used to compute dimensionless numbers
Author: UssopSniperKing
Project-URL: Homepage, https://github.com/UssopSniperKing/Nondimensionalization
Project-URL: Bug Tracker, https://github.com/UssopSniperKing/Nondimensionalization/issues
Classifier: Programming Language :: Python :: 3
Classifier: License :: OSI Approved :: MIT License
Classifier: Operating System :: OS Independent
Requires-Python: >=3.7
License-File: LICENSE
